[
    {
        "label": "Питомник",
        "items": [
            {
                "label": "Домашняя страница",
                "icon": "pi pi-fw pi-home",
                "routerLink": ["/home"]
            },
            {
                "label": "Собаки питомника",
                "icon": "pi pi-fw pi-home",
                "routerLink": ["/dogs"]
            }
        ]
    },
    {
        "label": "Пометы",
        "showAddButton": true,
        "items": [
            {
                "label": "Помет \"Г\"",
                "icon": "pi pi-fw pi-id-card",
                "routerLink": ["/litters"],
                "alias": "Г"
            },
            {
                "label": "Помет \"Ф\"",
                "icon": "pi pi-fw pi-id-card",
                "routerLink": ["/litters"],
                "alias": "Ф"
            }
        ]
    },
    {
        "label": "База знаний",
        "items": [
            {
                "label": "Основные документы",
                "icon": "pi pi-file-word",
                "routerLink": ["documents"]
            },
            {
                "label": "Памятки",
                "icon": "pi pi-file",
                "routerLink": ["memo"]
            }
        ]
    }
]
